CHANGES.txt
CREDITS.txt
LICENSE.txt
MANIFEST.in
README.rst
algorithms.txt
bootstrap.py
buildout.cfg
setup.py
todo.txt
doc/Makefile
doc/changes.rst
doc/conf.py
doc/index.rst
doc/make.bat
doc/usage.rst
jsonvalue/__init__.py
jsonvalue/core.py
jsonvalue/error.py
jsonvalue/schemaorg.py
jsonvalue.egg-info/PKG-INFO
jsonvalue.egg-info/SOURCES.txt
jsonvalue.egg-info/dependency_links.txt
jsonvalue.egg-info/not-zip-safe
jsonvalue.egg-info/requires.txt
jsonvalue.egg-info/top_level.txt
jsonvalue/tests/__init__.py
jsonvalue/tests/test_core.py