Metadata-Version: 1.0
Name: jsonvalue
Version: 0.1
Summary: Rich values for JSON
Home-page: UNKNOWN
Author: Martijn Faassen
Author-email: faassen@startifact.com
License: BSD
Keywords: jsonvalue
Platform: UNKNOWN
